aat/behavior-modelling/up_counter/beh_up_counter.v
module up_counter_3bit_beh (
    input clk,
    input reset,
    output reg [2:0] Q
);

    initial begin
        Q = 3'b000;
    end

    always @(posedge clk or posedge reset) begin
        if (reset)
            Q <= 3'b000;
        else
            Q <= Q + 1'b1;
    end

endmodule

beh/up_counter/beh_up_counter_tb.v
module beh_up_counter_tb;

    reg clk;
    wire [2:0] Q;

    up_counter_3bit_beh op (.clk(clk), .Q(Q));

    // Clock generation
    always #5 clk = ~clk;

    initial begin
        $dumpfile("beh_up_counter.vcd");
        $dumpvars(0,beh_up_counter_tb);
        clk = 0;
        #80 $finish;
    end

endmodule

aat/behavior-modelling/up_counter/beh_up_counter.vcd
$date
	Sun Dec 21 10:46:04 2025
$end
$version
	Icarus Verilog
$end
$timescale
	1s
$end
$scope module beh_up_counter_tb $end
$var wire 3 ! Q [2:0] $end
$var reg 1 " clk $end
$scope module op $end
$var wire 1 " clk $end
$var wire 1 # reset $end
$var reg 3 $ Q [2:0] $end
$upscope $end
$upscope $end
$enddefinitions $end
$comment Show the parameter values. $end
$dumpall
$end
#0
$dumpvars
b0 $
z#
0"
b0 !
$end
#5
b1 !
b1 $
1"
#10
0"
#15
b10 !
b10 $
1"
#20
0"
#25
b11 !
b11 $
1"
#30
0"
#35
b100 !
b100 $
1"
#40
0"
#45
b101 !
b101 $
1"
#50
0"
#55
b110 !
b110 $
1"
#60
0"
#65
b111 !
b111 $
1"
#70
0"
#75
b0 !
b0 $
1"
