flip_flop_ck/jk_ff.v
module jk_ff (
    input  wire J,
    input  wire K,
    input  wire clk,
    output reg  Q
);

    always @(posedge clk) begin
        case ({J, K})
            2'b00: Q <= Q;       // Hold
            2'b01: Q <= 0;       // Reset
            2'b10: Q <= 1;       // Set
            2'b11: Q <= ~Q;      // Toggle
        endcase
    end
endmodule

LD_devices/flip_flop_ck/jk_ff_tb.v
`timescale 1 ns / 1 ps
`include "jk_ff.v"

module jk_ff_tb;

    reg J, K, clk;
    wire Q;

    jk_ff uut (.J(J), .K(K), .clk(clk), .Q(Q));

    initial clk = 0;
    always #5 clk = ~clk;

    initial begin
    $dumpfile("jk_ff.vcd");
    $dumpvars(0, jk_ff_tb);
        J=0; K=0; #10;
        J=1; K=0; #10;  // Set
        J=0; K=1; #10;  // Reset
        J=1; K=1; #20;  // Toggle
        #20 $finish;
    end

endmodule

flip_flop_ck/jk_ff.vcd
$date
	Wed Dec 10 00:14:45 2025
$end
$version
	Icarus Verilog
$end
$timescale
	1ps
$end
$scope module jk_ff_tb $end
$var wire 1 ! Q $end
$var reg 1 " J $end
$var reg 1 # K $end
$var reg 1 $ clk $end
$scope module uut $end
$var wire 1 " J $end
$var wire 1 # K $end
$var wire 1 $ clk $end
$var reg 1 ! Q $end
$upscope $end
$upscope $end
$enddefinitions $end
$comment Show the parameter values. $end
$dumpall
$end
#0
$dumpvars
0$
0#
0"
x!
$end
#5000
1$
#10000
0$
1"
#15000
1!
1$
#20000
0$
1#
0"
#25000
0!
1$
#30000
0$
1"
#35000
1!
1$
#40000
0$
#45000
0!
1$
#50000
0$
#55000
1!
1$
#60000
0$
#65000
0!
1$
