LD_devices/flip_flop_ck/sr_ff.v
module sr_ff (
    input  wire S,
    input  wire R,
    input  wire clk,
    output reg  Q
);

    always @(posedge clk) begin
        case ({S, R})
            2'b00: Q <= Q;    // Hold
            2'b01: Q <= 0;    // Reset
            2'b10: Q <= 1;    // Set
            2'b11: Q <= 1'bx; // Invalid condition
        endcase
    end
endmodule

flip_flop_ck/sr_ff_tb.v
`timescale 1 ns / 1 ps
`include "sr_ff.v"
module sr_ff_tb;

    reg S, R, clk;
    wire Q;

    sr_ff uut (.S(S), .R(R), .clk(clk), .Q(Q));

    initial clk = 0;
    always #5 clk = ~clk;  // Clock

    initial begin
    $dumpfile("sr_ff.vcd");
    $dumpvars(0, sr_ff_tb);
        S=0; R=0; #10;
        S=1; R=0; #10;
        S=0; R=1; #10;
        S=0; R=0; #10;
        S=1; R=1; #10;   // Invalid
        #20 $finish;
    end

endmodule

flip_flop_ck/sr_ff.vcd
$date
	Wed Dec 10 00:13:05 2025
$end
$version
	Icarus Verilog
$end
$timescale
	1ps
$end
$scope module sr_ff_tb $end
$var wire 1 ! Q $end
$var reg 1 " R $end
$var reg 1 # S $end
$var reg 1 $ clk $end
$scope module uut $end
$var wire 1 " R $end
$var wire 1 # S $end
$var wire 1 $ clk $end
$var reg 1 ! Q $end
$upscope $end
$upscope $end
$enddefinitions $end
$comment Show the parameter values. $end
$dumpall
$end
#0
$dumpvars
0$
0#
0"
x!
$end
#5000
1$
#10000
0$
1#
#15000
1!
1$
#20000
0$
1"
0#
#25000
0!
1$
#30000
0$
0"
#35000
1$
#40000
0$
1"
1#
#45000
x!
1$
