aat/behavior-modelling/jkff/beh_jkff.v
module jk_ff_beh (
    input J,
    input K,
    input clk,
    output reg Q,
    output reg Qbar
);

    always @(posedge clk) begin
        case ({J, K})
            2'b00: begin
                Q    <= Q;        // Hold
                Qbar <= Qbar;
            end
            2'b01: begin
                Q    <= 0;        // Reset
                Qbar <= 1;
            end
            2'b10: begin
                Q    <= 1;        // Set
                Qbar <= 0;
            end
            2'b11: begin
                Q    <= ~Q;       // Toggle
                Qbar <= ~Qbar;
            end
        endcase
    end

endmodule

aat/behavior-modelling/jkff/beh_jkff_tb.v
module beh_jkff_tb;

    reg J, K, clk;
    wire Q, Qbar;

    jk_ff_beh op (.J(J), .K(K), .clk(clk),
                      .Q(Q), .Qbar(Qbar)
    );

    // Clock generation
    always #5 clk = ~clk;

    initial begin
        $dumpfile("beh_jkff.vcd");
        $dumpvars(0, beh_jkff_tb);
        clk = 0;
        J = 0; K = 0;      // Hold
        #10 J = 0; K = 1;  // Reset
        #10 J = 1; K = 0;  // Set
        #10 J = 1; K = 1;  // Toggle
        #20 $finish;
    end

endmodule

aat/behavior-modelling/jkff/beh_jkff.vcd
$date
	Sun Dec 21 00:06:48 2025
$end
$version
	Icarus Verilog
$end
$timescale
	1s
$end
$scope module beh_jkff_tb $end
$var wire 1 ! Qbar $end
$var wire 1 " Q $end
$var reg 1 # J $end
$var reg 1 $ K $end
$var reg 1 % clk $end
$scope module op $end
$var wire 1 # J $end
$var wire 1 $ K $end
$var wire 1 % clk $end
$var reg 1 " Q $end
$var reg 1 ! Qbar $end
$upscope $end
$upscope $end
$enddefinitions $end
$comment Show the parameter values. $end
$dumpall
$end
#0
$dumpvars
0%
0$
0#
x"
x!
$end
#5
1%
#10
0%
1$
#15
1!
0"
1%
#20
0%
0$
1#
#25
0!
1"
1%
#30
0%
1$
#35
1!
0"
1%
#40
0%
#45
0!
1"
1%
