aat/behavior-modelling/jkff/struct_jkff.v
module jk_ff_struct (
    input J,
    input K,
    input clk,
    output Q,
    output Qbar
);

    wire S, R;

    // Logic for S and R
    and (S, J, clk, Qbar);
    and (R, K, clk, Q);

    // Cross-coupled NOR latch
    nor (Q, R, Qbar);
    nor (Qbar, S, Q);

endmodule

aat/behavior-modelling/jkff/struct_jkff_tb.v
module struct_jkff_tb;

    reg J, K, clk;
    wire Q, Qbar;

    jk_ff_struct op (.J(J), .K(K), .clk(clk),
                      .Q(Q), .Qbar(Qbar)
    );

    // Clock generation
    always #5 clk = ~clk;

    initial begin
        $dumpfile("struct_jkff.vcd");
        $dumpvars(0, struct_jkff_tb);
        clk = 0;
        J = 0; K = 0;      // Hold
        #10 J = 0; K = 1;  // Reset
        #10 J = 1; K = 0;  // Set
        #10 J = 1; K = 1;  // Toggle
        #20 $finish;
    end

endmodule

aat/behavior-modelling/jkff/struct_jkff.vcd
$date
	Sun Dec 21 19:37:59 2025
$end
$version
	Icarus Verilog
$end
$timescale
	1s
$end
$scope module struct_jkff_tb $end
$var wire 1 ! Qbar $end
$var wire 1 " Q $end
$var reg 1 # J $end
$var reg 1 $ K $end
$var reg 1 % clk $end
$scope module op $end
$var wire 1 # J $end
$var wire 1 $ K $end
$var wire 1 " Q $end
$var wire 1 ! Qbar $end
$var wire 1 & R $end
$var wire 1 ' S $end
$var wire 1 % clk $end
$upscope $end
$upscope $end
$enddefinitions $end
$comment Show the parameter values. $end
$dumpall
$end
#0
$dumpvars
0'
0&
0%
0$
0#
x"
x!
$end
#5
1%
#10
0%
1$
#15
x&
1%
#20
0&
0%
0$
1#
#25
x'
1%
#30
0'
0%
1$
#35
x'
x&
1%
#40
0'
0&
0%
#45
x'
x&
1%
#50
0'
0&
0%
